simple_calculator/__init__.py
simple_calculator/advanced.py
simple_calculator/calculator.py
simple_calculator_demo_0121-0.1.0.dist-info/METADATA
simple_calculator_demo_0121-0.1.0.dist-info/WHEEL
simple_calculator_demo_0121-0.1.0.dist-info/top_level.txt
simple_calculator_demo_0121-0.1.0.dist-info/RECORD
